rtacpy/__init__.py
rtacpy/calc_rta_n.py
rtacpy/calc_rtac_n.py
rtacpy/independence_test.py
rtacpy-0.1.5.dist-info/licenses/LICENSE
rtacpy-0.1.5.dist-info/METADATA
rtacpy-0.1.5.dist-info/WHEEL
rtacpy-0.1.5.dist-info/top_level.txt
rtacpy-0.1.5.dist-info/RECORD
