Metadata-Version: 2.4
Name: rtacpy
Version: 0.1.5
Summary: A Python package for calculating RTAC, the rank-transform area coverage coefficient of correlation.
Author: Itai Pelles
License: Apache-2.0
Project-URL: Homepage, https://github.com/itaipelles/rtacpy
Project-URL: Changelog, https://github.com/itaipelles/rtacpy/releases
Project-URL: Issues, https://github.com/itaipelles/rtacpy/issues
Project-URL: CI, https://github.com/itaipelles/rtacpy/actions
Classifier: License :: OSI Approved :: Apache Software License
Requires-Python: <3.13,>=3.9
License-File: LICENSE
Requires-Dist: numpy
Requires-Dist: numba
Provides-Extra: test
Requires-Dist: pytest; extra == "test"
Dynamic: license-file
